repo_helper_github/__init__.py
repo_helper_github/_github.py
repo_helper_github/_types.py
repo_helper_github/cli.py
repo_helper_github/exceptions.py
repo_helper_github/options.py
repo_helper_github/py.typed
repo_helper_github/secret_validation.py
repo_helper_github-0.9.0.dist-info/LICENSE
repo_helper_github-0.9.0.dist-info/METADATA
repo_helper_github-0.9.0.dist-info/WHEEL
repo_helper_github-0.9.0.dist-info/entry_points.txt
repo_helper_github-0.9.0.dist-info/RECORD
