Metadata-Version: 2.2
Name: repo-helper-github
Version: 0.9.0
Summary: Manage GitHub repositories with repo-helper.
Author-email: Dominic Davis-Foster <dominic@davis-foster.co.uk>
License: MIT
Keywords: github,repo-helper
Home-page: https://github.com/repo-helper/repo_helper_github
Project-URL: Issue Tracker, https://github.com/repo-helper/repo_helper_github/issues
Project-URL: Source Code, https://github.com/repo-helper/repo_helper_github
Project-URL: Documentation, https://repo-helper-github.readthedocs.io/en/latest
Platform: Windows
Platform: macOS
Platform: Linux
Classifier: Development Status :: 4 - Beta
Classifier: Environment :: Console
Classifier: Intended Audience :: Developers
Classifier: License :: OSI Approved :: MIT License
Classifier: Operating System :: OS Independent
Classifier: Programming Language :: Python
Classifier: Programming Language :: Python :: 3 :: Only
Classifier: Programming Language :: Python :: 3.7
Classifier: Programming Language :: Python :: 3.8
Classifier: Programming Language :: Python :: 3.9
Classifier: Programming Language :: Python :: 3.10
Classifier: Programming Language :: Python :: 3.11
Classifier: Programming Language :: Python :: 3.12
Classifier: Programming Language :: Python :: Implementation :: CPython
Classifier: Topic :: Software Development :: Version Control :: Git
Classifier: Typing :: Typed
Requires-Python: >=3.7
Requires-Dist: click>=7.1.2
Requires-Dist: consolekit>=1.1.2
Requires-Dist: deprecation-alias>=0.2.0
Requires-Dist: domdf-python-tools>=2.0.0
Requires-Dist: dulwich!=0.20.7,!=0.20.8,!=0.20.9,>=0.20.5
Requires-Dist: github3-py>=1.3.0
Requires-Dist: github3-utils>=0.5.0
Requires-Dist: packaging>=21.0
Requires-Dist: pymacaroons>=0.13.0
Requires-Dist: repo-helper>=2020.12.18
Requires-Dist: southwark>=0.4.0
Requires-Dist: typing-extensions>=3.7.4.3
